givapi.py
givapi-0.4.1.dist-info/LICENSE
givapi-0.4.1.dist-info/METADATA
givapi-0.4.1.dist-info/WHEEL
givapi-0.4.1.dist-info/RECORD
